setup.py
scripts/wdl
scripts/wdl2dot
wdl/__init__.py
wdl/binding.py
wdl/engine.py
wdl/main.py
wdl/parser.py
wdl/spec.py
wdl/types.py
wdl/util.py
wdl/values.py
wdl.egg-info/PKG-INFO
wdl.egg-info/SOURCES.txt
wdl.egg-info/dependency_links.txt
wdl.egg-info/requires.txt
wdl.egg-info/top_level.txt