Metadata-Version: 1.1
Name: wdl
Version: 1.0.19
Summary: Parse and Process WDL Files
Home-page: http://github.com/broadinstitute/wdl
Author: Scott Frazer
Author-email: sfrazer@broadinstitute.org
License: MIT
Keywords: Workflow,Task
Platform: UNKNOWN
Classifier: License :: OSI Approved :: MIT License
Classifier: Programming Language :: Python
Classifier: Development Status :: 4 - Beta
Classifier: Intended Audience :: Developers
Classifier: Natural Language :: English
